jupyterlab_friendly_traceback/__init__.py
jupyterlab_friendly_traceback/_version.py
jupyterlab_friendly_traceback-0.4.0.data/data/share/jupyter/labextensions/jupyterlab-friendly-traceback/package.json
jupyterlab_friendly_traceback-0.4.0.data/data/share/jupyter/labextensions/jupyterlab-friendly-traceback/static/300.3c077d6f54b704fd5eb9.js
jupyterlab_friendly_traceback-0.4.0.data/data/share/jupyter/labextensions/jupyterlab-friendly-traceback/static/804.9505e9862291289d8bd4.js
jupyterlab_friendly_traceback-0.4.0.data/data/share/jupyter/labextensions/jupyterlab-friendly-traceback/static/remoteEntry.4c9462f95c99c6fdef2a.js
jupyterlab_friendly_traceback-0.4.0.data/data/share/jupyter/labextensions/jupyterlab-friendly-traceback/static/style.js
jupyterlab_friendly_traceback-0.4.0.data/data/share/jupyter/labextensions/jupyterlab-friendly-traceback/static/third-party-licenses.json
jupyterlab_friendly_traceback-0.4.0.data/data/share/jupyter/labextensions/jupyterlab-friendly-traceback/install.json
jupyterlab_friendly_traceback-0.4.0.dist-info/METADATA
jupyterlab_friendly_traceback-0.4.0.dist-info/WHEEL
jupyterlab_friendly_traceback-0.4.0.dist-info/licenses/LICENSE
jupyterlab_friendly_traceback-0.4.0.dist-info/RECORD
