Metadata-Version: 2.1
Name: jupyterlab_friendly_traceback
Version: 0.4.0
Summary: Add a boutton to activate/deactivate friendly traceback
Project-URL: Homepage, https://github.com/logilab/jupyterlab-friendly-traceback
Project-URL: Bug Tracker, https://github.com/logilab/jupyterlab-friendly-traceback/issues
Project-URL: Repository, https://github.com/logilab/jupyterlab-friendly-traceback
Author-email: Logilab <ogiorgis@logilab.fr>
License: BSD 3-Clause License
License-File: LICENSE
Classifier: Framework :: Jupyter
Classifier: Framework :: Jupyter :: JupyterLab
Classifier: Framework :: Jupyter :: JupyterLab :: 4
Classifier: Framework :: Jupyter :: JupyterLab :: Extensions
Classifier: Framework :: Jupyter :: JupyterLab :: Extensions :: Prebuilt
Classifier: License :: OSI Approved :: BSD License
Classifier: Programming Language :: Python
Classifier: Programming Language :: Python :: 3
Classifier: Programming Language :: Python :: 3.8
Classifier: Programming Language :: Python :: 3.9
Classifier: Programming Language :: Python :: 3.10
Classifier: Programming Language :: Python :: 3.11
Requires-Python: >=3.8
Requires-Dist: friendly
Requires-Dist: jupyterlab
